larkjs/__main__.py
larkjs/lark.js
lark_js-0.1.4.dist-info/entry_points.txt
lark_js-0.1.4.dist-info/LICENSE
lark_js-0.1.4.dist-info/WHEEL
lark_js-0.1.4.dist-info/METADATA
lark_js-0.1.4.dist-info/RECORD
